Metadata-Version: 1.1
Name: kubewait
Version: 0.2.1
Summary: Pause container init until required kube services are ready,
Home-page: https://github.com/joeblackwaslike/kubewait
Author: Joe Black
Author-email: joeblack949@gmail.com
License: Apache 2.0
Download-URL: https://github.com/joeblackwaslike/kubewait/tarball/0.2.1
Keywords: kubernetes,clustering,init-container
Platform: UNKNOWN
Classifier: Development Status :: 3 - Alpha
Classifier: Intended Audience :: Developers
Classifier: Operating System :: OS Independent
Classifier: Natural Language :: English
Classifier: License :: OSI Approved :: Apache Software License
Classifier: Programming Language :: Python :: 3 :: Only
Classifier: Topic :: Internet :: WWW/HTTP
Classifier: Topic :: System :: Clustering
